{
    "image": "/weston",
    "registry": "commontorizon",
    "version": "next",
    "multiarch": true,
    "machines": [
        {
            "name": "generic",
            "arch": [
                "arm",
                "arm64",
                "amd64"
            ],
            "BASE_REGISTRY": "torizon",
            "BASE_IMAGE": "/weston",
            "BASE_VERSION": "next",
            "GPU": ""
        },
        {
            "name": "arm64-imx8",
            "arch": [
                "arm64"
            ],
            "BASE_REGISTRY": "torizon",
            "BASE_IMAGE": "/weston",
            "BASE_VERSION": "next",
            "GPU": "-imx8"
        },
        {
            "name": "arm64-am62",
            "arch": [
                "arm64"
            ],
            "BASE_REGISTRY": "torizon",
            "BASE_IMAGE": "/weston",
            "BASE_VERSION": "next",
            "GPU": "-am62"
        }
    ]
}
